Workbook

Sheet BreakEvenModel
B2: Green Africa Hub - Break-Even Model (Updated)
B3: Base case aligned to revised plan targeting c. £55k revenue in Year 3
B5: Assumptions | E5: Sheet Index
B6: Starting capital (£) | C6: 1500 | E6: BreakEvenModel
B7: Workshop ticket price (£) | C7: 20 | E7: 5yr Projection
B8: Average participants per workshop | C8: 10 | E8: Automated Summary
B9: Workshop revenue (£) | C9: =C7*C8 -> 200
B10: Venue cost per workshop (£) | C10: 112
B11: Ingredients/materials per workshop (£) | C11: 60
B12: Other variable cost per workshop (£) | C12: 10
B13: Total variable cost per workshop (£) | C13: =C10+C11+C12 -> 182
B14: Contribution per workshop (£) | C14: =C9-C13 -> 18
B15: Fixed monthly costs (£) | C15: 1200
B16: Sessions-only break-even (per month) | C16: =ROUNDUP(C15/C14,0) -> 67
B17: Monthly financial break-even month | C17: 5
B20: Revenue stream | C20: Year 1 (£) | D20: Year 2 (£) | E20: Year 3 (£)
B21: In-person sessions | C21: 4500 | D21: 9000 | E21: 12000
B22: Digital subscriptions | C22: 1200 | D22: 3600 | E22: 5000
B23: Kitchen memberships | C23: 1500 | D23: 3000 | E23: 4000
B24: Equipment commissions | C24: 800 | D24: 2000 | E24: 3500
B25: B2B events & consulting | C25: 3700 | D25: 12600 | E25: 30000
B26: Total revenue | C26: =SUM(C21:C25) -> 11700 | D26: =SUM(D21:D25) -> 30200 | E26: =SUM(E21:E25) -> 54500
B29: Metric | C29: Value
B30: Starting capital (£) | C30: =C6 -> 1500
B31: Year 1 revenue (£) | C31: =C26 -> 11700
B32: Year 2 revenue (£) | C32: =D26 -> 30200
B33: Year 3 revenue (£) | C33: =E26 -> 54500
B34: Total 3-year revenue (£) | C34: =SUM(C26:E26) -> 96400
B35: Year 1 profit (£) | C35: 4093
B36: Year 2 profit (£) | C36: 19038
B37: Year 3 profit (£) | C37: 21144
B38: Total 3-year profit (£) | C38: =SUM(C35:C37) -> 44275
B39: Final cumulative cash (£) | C39: =C38+C30 -> 45775
B40: Break-even month | C40: =C17 -> 5
B43: Notes
B44: This workbook reflects the revised business-plan base case targeting c. £55k Year 3 revenue.
B45: Community workshops remain priced at £20; higher total revenue comes from subscriptions, memberships and B2B consulting.

Sheet 5yr Projection
B2: Green Africa Hub - 5 Year Financial Projection
B3: Years 1-3 align with the revised business-plan base case; Years 4-5 show onward scaling.
B5: Revenue stream | C5: Year 1 | D5: Year 2 | E5: Year 3 | F5: Year 4 | G5: Year 5
B6: In-person sessions | C6: =BreakEvenModel!C21 -> 4500 | D6: =BreakEvenModel!D21 -> 9000 | E6: =BreakEvenModel!E21 -> 12000 | F6: =E6*1.25 -> 15000 | G6: =F6*1.2 -> 18000
B7: Digital subscriptions | C7: =BreakEvenModel!C22 -> 1200 | D7: =BreakEvenModel!D22 -> 3600 | E7: =BreakEvenModel!E22 -> 5000 | F7: =E7*1.3 -> 6500 | G7: =F7*1.25 -> 8125
B8: Kitchen memberships | C8: =BreakEvenModel!C23 -> 1500 | D8: =BreakEvenModel!D23 -> 3000 | E8: =BreakEvenModel!E23 -> 4000 | F8: =E8*1.25 -> 5000 | G8: =F8*1.2 -> 6000
B9: Equipment commissions | C9: =BreakEvenModel!C24 -> 800 | D9: =BreakEvenModel!D24 -> 2000 | E9: =BreakEvenModel!E24 -> 3500 | F9: =E9*1.2 -> 4200 | G9: =F9*1.15 -> 4830
B10: B2B events & consulting | C10: =BreakEvenModel!C25 -> 3700 | D10: =BreakEvenModel!D25 -> 12600 | E10: =BreakEvenModel!E25 -> 30000 | F10: =E10*1.2 -> 36000 | G10: =F10*1.2 -> 43200
B11: Total revenue | C11: =SUM(C6:C10) -> 11700 | D11: =SUM(D6:D10) -> 30200 | E11: =SUM(E6:E10) -> 54500 | F11: =SUM(F6:F10) -> 66700 | G11: =SUM(G6:G10) -> 80155
B14: Metric | C14: Year 1 | D14: Year 2 | E14: Year 3 | F14: Year 4 | G14: Year 5
B15: Profit | C15: 4093 | D15: 19038 | E15: 21144 | F15: =F11*0.38 -> 25346 | G15: =G11*0.38 -> 30458.9
B16: Cumulative profit | C16: =C16 -> 0 | D16: =C16+D16 -> 0 | E16: =E16+E17 -> 0 | F16: =F16+F17 -> 0 | G16: =G16+G17 -> 0

Sheet Automated Summary
B2: Green Africa Hub - Automated Financial Summary
B4: Metric | C4: Value
B5: Starting capital (£) | C5: =BreakEvenModel!C6 -> 1500
B6: Year 1 revenue (£) | C6: ='5yr Projection'!C11 -> 11700
B7: Year 2 revenue (£) | C7: ='5yr Projection'!D11 -> 30200
B8: Year 3 revenue (£) | C8: ='5yr Projection'!E11 -> 54500
B9: Year 4 revenue (£) | C9: ='5yr Projection'!F11 -> 66700
B10: Year 5 revenue (£) | C10: ='5yr Projection'!G11 -> 80155
B11: Total 5-year revenue (£) | C11: =SUM(C6:C10) -> 243255
B12: Year 1 profit (£) | C12: 4093
B13: Year 2 profit (£) | C13: 19038
B14: Year 3 profit (£) | C14: 21144
B15: Year 4 profit (£) | C15: ='5yr Projection'!F17 -> 0
B16: Year 5 profit (£) | C16: ='5yr Projection'!G17 -> 0
B17: Total 5-year profit (£) | C17: =SUM(C12:C16) -> 44275
B18: Break-even month | C18: =BreakEvenModel!C17 -> 5
