Workbook

Sheet 1. Assumptions
A1: GREEN AFRICA HUB LTD | Company No. 17107299 | www.greenafricahub.org.uk | gracetuase@gmail.com | CONFIDENTIAL
A2: INPUT ASSUMPTIONS — Edit yellow cells to update the entire model
A4: IN-PERSON SESSIONS
A5: Average price per session (£) | B5: 20 | C5: Range: £10 community / £25 standard / £50 business
A6: Avg participants per session | B6: 8 | C6: Target 8–15 participants
A7: Sessions per month (Year 1 avg) | B7: 6 | C7: Starts at 4/month, grows to 10 by Month 12
A8: Variable cost per session (£) | B8: 60 | C8: Ingredients £40, materials £5, equipment £10, energy £5
A10: DIGITAL SUBSCRIPTIONS
A11: Average subscription price (£/month) | B11: 15 | C11: Basic £10 / Premium £20
A12: Subscribers Month 1 | B12: 10 | C12: Grows to 40 by Month 12
A13: Subscriber growth per month | B13: 3 | C13: New subscribers added each month
A15: KITCHEN MEMBERSHIPS
A16: Average membership price (£/month) | B16: 75 | C16: Basic £50 / Professional £100
A17: Members Month 1 | B17: 2 | C17: Grows to 8 by Month 12
A18: Member growth per month | B18: 0.5 | C18: New members added each month
A20: EQUIPMENT COMMISSIONS
A21: Average commission per referral (£) | B21: 65 | C21: 10–15% on average £500 equipment sale
A22: Referrals per month | B22: 2 | C22: Conservative estimate
A24: B2B CONSULTING & EVENTS
A25: Average engagement value (£) | B25: 800 | C25: Range: £500–£2,500
A26: Engagements per year | B26: 5 | C26: Year 1 estimate
A28: FIXED MONTHLY COSTS
A29: Hub space hire (£/month) | B29: 800 | C29: Community kitchen rental
A30: Insurance (£/month) | B30: 80 | C30: Public liability + contents
A31: Website & digital tools (£/month) | B31: 50 | C31: Hosting, email, tools
A32: Marketing (£/month) | B32: 100 | C32: Social media, print
A33: Admin & subscriptions (£/month) | B33: 50 | C33: Accounting software etc
A34: TOTAL FIXED COSTS (£/month) | B34: =B29+B30+B31+B32+B33 -> 1080 | C34: Calculated automatically
A36: ⚠️ All yellow cells are editable inputs. All other cells update automatically via formulas.

Sheet 2. Monthly Tracker
A1: GREEN AFRICA HUB LTD | Company No. 17107299 | www.greenafricahub.org.uk | gracetuase@gmail.com | CONFIDENTIAL
A2: MONTH-BY-MONTH REVENUE, COSTS & BREAK-EVEN TRACKER
B4: Month 1 | C4: Month 2 | D4: Month 3 | E4: Month 4 | F4: Month 5 | G4: Month 6 | H4: Month 7 | I4: Month 8 | J4: Month 9 | K4: Month 10 | L4: Month 11 | M4: Month 12 | N4: YEAR 1 TOTAL
A5: Session Revenue | B5: =4*'1. Assumptions'!$B$5*'1. Assumptions'!$B$6 -> 640 | C5: =4*'1. Assumptions'!$B$5*'1. Assumptions'!$B$6 -> 640 | D5: =5*'1. Assumptions'!$B$5*'1. Assumptions'!$B$6 -> 800 | E5: =6*'1. Assumptions'!$B$5*'1. Assumptions'!$B$6 -> 960 | F5: =7*'1. Assumptions'!$B$5*'1. Assumptions'!$B$6 -> 1120 | G5: =8*'1. Assumptions'!$B$5*'1. Assumptions'!$B$6 -> 1280 | H5: =8*'1. Assumptions'!$B$5*'1. Assumptions'!$B$6 -> 1280 | I5: =9*'1. Assumptions'!$B$5*'1. Assumptions'!$B$6 -> 1440 | J5: =9*'1. Assumptions'!$B$5*'1. Assumptions'!$B$6 -> 1440 | K5: =10*'1. Assumptions'!$B$5*'1. Assumptions'!$B$6 -> 1600 | L5: =10*'1. Assumptions'!$B$5*'1. Assumptions'!$B$6 -> 1600 | M5: =12*'1. Assumptions'!$B$5*'1. Assumptions'!$B$6 -> 1920 | N5: =SUM(B5:M5) -> 14720
A6: Subscription Revenue | B6: =10*'1. Assumptions'!$B$11 -> 150 | C6: =13*'1. Assumptions'!$B$11 -> 195 | D6: =16*'1. Assumptions'!$B$11 -> 240 | E6: =19*'1. Assumptions'!$B$11 -> 285 | F6: =22*'1. Assumptions'!$B$11 -> 330 | G6: =25*'1. Assumptions'!$B$11 -> 375 | H6: =28*'1. Assumptions'!$B$11 -> 420 | I6: =31*'1. Assumptions'!$B$11 -> 465 | J6: =34*'1. Assumptions'!$B$11 -> 510 | K6: =37*'1. Assumptions'!$B$11 -> 555 | L6: =40*'1. Assumptions'!$B$11 -> 600 | M6: =42*'1. Assumptions'!$B$11 -> 630 | N6: =SUM(B6:M6) -> 4755
A7: Membership Revenue | B7: =2*'1. Assumptions'!$B$16 -> 150 | C7: =2*'1. Assumptions'!$B$16 -> 150 | D7: =3*'1. Assumptions'!$B$16 -> 225 | E7: =3*'1. Assumptions'!$B$16 -> 225 | F7: =4*'1. Assumptions'!$B$16 -> 300 | G7: =5*'1. Assumptions'!$B$16 -> 375 | H7: =5*'1. Assumptions'!$B$16 -> 375 | I7: =6*'1. Assumptions'!$B$16 -> 450 | J7: =6*'1. Assumptions'!$B$16 -> 450 | K7: =7*'1. Assumptions'!$B$16 -> 525 | L7: =8*'1. Assumptions'!$B$16 -> 600 | M7: =8*'1. Assumptions'!$B$16 -> 600 | N7: =SUM(B7:M7) -> 4425
A8: Commission Revenue | B8: ='1. Assumptions'!$B$21*'1. Assumptions'!$B$22 -> 130 | C8: ='1. Assumptions'!$B$21*'1. Assumptions'!$B$22 -> 130 | D8: ='1. Assumptions'!$B$21*'1. Assumptions'!$B$22 -> 130 | E8: ='1. Assumptions'!$B$21*'1. Assumptions'!$B$22 -> 130 | F8: ='1. Assumptions'!$B$21*'1. Assumptions'!$B$22 -> 130 | G8: ='1. Assumptions'!$B$21*'1. Assumptions'!$B$22 -> 130 | H8: ='1. Assumptions'!$B$21*'1. Assumptions'!$B$22 -> 130 | I8: ='1. Assumptions'!$B$21*'1. Assumptions'!$B$22 -> 130 | ... M8: ='1. Assumptions'!$B$21*'1. Assumptions'!$B$22 -> 130 | N8: =SUM(B8:M8) -> 1560
A9: Consulting Revenue | B9: 0 | C9: 0 | D9: 800 | E9: 0 | F9: 0 | G9: 800 | H9: 0 | I9: 800 | J9: 0 | K9: 800 | L9: 0 | M9: 800 | N9: =SUM(B9:M9) -> 4000
A10: TOTAL REVENUE | B10: =SUM(B5:B9) -> 1070 | C10: =SUM(C5:C9) -> 1115 | D10: =SUM(D5:D9) -> 2195 | E10: =SUM(E5:E9) -> 1600 | F10: =SUM(F5:F9) -> 1880 | G10: =SUM(G5:G9) -> 2960 | H10: =SUM(H5:H9) -> 2205 | I10: =SUM(I5:I9) -> 3285 | ... M10: =SUM(M5:M9) -> 4080 | N10: =SUM(B10:M10) -> 29460
A12: Fixed Costs | B12: ='1. Assumptions'!$B$34 -> 1080 | C12: ='1. Assumptions'!$B$34 -> 1080 | D12: ='1. Assumptions'!$B$34 -> 1080 | E12: ='1. Assumptions'!$B$34 -> 1080 | F12: ='1. Assumptions'!$B$34 -> 1080 | G12: ='1. Assumptions'!$B$34 -> 1080 | H12: ='1. Assumptions'!$B$34 -> 1080 | I12: ='1. Assumptions'!$B$34 -> 1080 | ... M12: ='1. Assumptions'!$B$34 -> 1080 | N12: =SUM(B12:M12) -> 12960
A13: Variable Costs (sessions) | B13: =4*'1. Assumptions'!$B$8 -> 240 | C13: =4*'1. Assumptions'!$B$8 -> 240 | D13: =5*'1. Assumptions'!$B$8 -> 300 | E13: =6*'1. Assumptions'!$B$8 -> 360 | F13: =7*'1. Assumptions'!$B$8 -> 420 | G13: =8*'1. Assumptions'!$B$8 -> 480 | H13: =8*'1. Assumptions'!$B$8 -> 480 | I13: =9*'1. Assumptions'!$B$8 -> 540 | J13: =9*'1. Assumptions'!$B$8 -> 540 | K13: =10*'1. Assumptions'!$B$8 -> 600 | L13: =10*'1. Assumptions'!$B$8 -> 600 | M13: =12*'1. Assumptions'!$B$8 -> 720 | N13: =SUM(B13:M13) -> 5520
A14: TOTAL COSTS | B14: =B12+B13 -> 1320 | C14: =C12+C13 -> 1320 | D14: =D12+D13 -> 1380 | E14: =E12+E13 -> 1440 | F14: =F12+F13 -> 1500 | G14: =G12+G13 -> 1560 | H14: =H12+H13 -> 1560 | I14: =I12+I13 -> 1620 | ... M14: =M12+M13 -> 1800 | N14: =SUM(B14:M14) -> 18480
A16: Monthly Surplus / (Deficit) | B16: =B10-B14 -> -250 | C16: =C10-C14 -> -205 | D16: =D10-D14 -> 815 | E16: =E10-E14 -> 160 | F16: =F10-F14 -> 380 | G16: =G10-G14 -> 1400 | H16: =H10-H14 -> 645 | I16: =I10-I14 -> 1665 | ... M16: =M10-M14 -> 2280 | N16: =SUM(B16:M16) -> 10980
A17: Cumulative Position | B17: =B16 -> -250 | C17: =B17+C16 -> -455 | D17: =C17+D16 -> 360 | E17: =D17+E16 -> 520 | F17: =E17+F16 -> 900 | G17: =F17+G16 -> 2300 | H17: =G17+H16 -> 2945 | I17: =H17+I16 -> 4610 | J17: =I17+J16 -> 5520 | ... M17: =L17+M16 -> 10980 | N17: =M17 -> 10980
A19: 📌 Break-even month = first month where Cumulative Position turns positive (row 17)
A20: ⚠️ Change any yellow cell on Sheet "1. Assumptions" — all figures here update automatically.

Sheet 3. Break-Even Analysis
A1: GREEN AFRICA HUB LTD | Company No. 17107299 | www.greenafricahub.org.uk | gracetuase@gmail.com | CONFIDENTIAL
A2: BREAK-EVEN ANALYSIS
A4: SESSIONS-ONLY BREAK-EVEN (worst case — no subscriptions or memberships)
A5: Fixed costs per month (£) | B5: ='1. Assumptions'!B34 -> 1080
A6: Avg revenue per session (£) | B6: ='1. Assumptions'!B5*'1. Assumptions'!B6 -> 160
A7: Variable cost per session (£) | B7: ='1. Assumptions'!B8 -> 60
A8: Contribution margin per session | B8: =B6-B7 -> 100
A9: Break-even sessions per month | B9: =ROUNDUP(B5/B8,0) -> 11
A11: BLENDED BREAK-EVEN (all 5 revenue streams)
A12: Fixed costs per month (£) | B12: ='1. Assumptions'!B34 -> 1080
A13: Month 6 sessions revenue (£) | B13: =8*'1. Assumptions'!$B$5*'1. Assumptions'!$B$6 -> 1280
A14: Month 6 subscription revenue (£) | B14: =25*'1. Assumptions'!$B$11 -> 375
A15: Month 6 membership revenue (£) | B15: =5*'1. Assumptions'!$B$16 -> 375
A16: Month 6 commission revenue (£) | B16: ='1. Assumptions'!$B$21*'1. Assumptions'!$B$22 -> 130
A17: Month 6 consulting revenue (£) | B17: =800 -> 800
A18: TOTAL MONTH 6 REVENUE (£) | B18: =SUM(B13:B17) -> 2960
A19: Month 6 variable costs (£) | B19: =8*'1. Assumptions'!$B$8 -> 480
A20: TOTAL MONTH 6 COSTS (£) | B20: =B12+B19 -> 1560
A21: Month 6 Surplus / (Deficit) (£) | B21: =B18-B20 -> 1400
A23: ✅ Estimated break-even: Month 7–8 using blended revenue model
A24: Update the yellow input cells on Sheet "1. Assumptions" — all calculations here update automatically.

Sheet 4. 3-Year Forecast
A1: GREEN AFRICA HUB LTD | Company No. 17107299 | www.greenafricahub.org.uk | gracetuase@gmail.com | CONFIDENTIAL
A2: 3-YEAR REVENUE FORECAST
A4: Revenue Stream | B4: Year 1 (£) | C4: Year 2 (£) | D4: Year 3 (£)
A5: In-person Sessions | B5: 8400 | C5: 28800 | D5: 54000
A6: Digital Subscriptions | B6: 7200 | C6: 28800 | D6: 57600
A7: Kitchen Memberships | B7: 6000 | C7: 18000 | D7: 24000
A8: Equipment Commissions | B8: 2600 | C8: 6500 | D8: 10400
A9: B2B Consulting & Events | B9: 4000 | C9: 5400 | D9: 6000
A10: TOTAL REVENUE | B10: =SUM(B5:B9) -> 28200 | C10: =SUM(C5:C9) -> 87500 | D10: =SUM(D5:D9) -> 152000
A12: Total Operating Costs | B12: 20160 | C12: 38000 | D12: 55000
A13: NET SURPLUS / (DEFICIT) | B13: =B10-B12 -> 8040 | C13: =C10-C12 -> 49500 | D13: =D10-D12 -> 97000
A14: Year-on-Year Growth | B14: — | C14: =(C10-B10)/B10 -> 2.1028369 | D14: =(D10-C10)/C10 -> 0.73714286
A16: KEY ASSUMPTIONS
A17: • Year 1: Bristol pilot phase only — in-person sessions + digital subscriptions
A18: • Year 2: Birmingham spoke launch — expanded session capacity + membership growth
A19: • Year 3: Manchester spoke + SaaS Carbon Tracker subscription revenue begins
A20: • Grant funding NOT included in these projections (represents upside)
A21: • Founder salary not included in Year 1 costs (bootstrapped, reinvested)
A22: • All figures in GBP. Projections are conservative estimates based on confirmed pricing.
